{
  "version": "1.0",
  "timestamp": "2026-04-02T10:31:18.054Z",
  "phase": "09",
  "phase_name": "ai-metadata-auto-fill",
  "phase_dir": ".planning/phases/09-ai-metadata-auto-fill",
  "plan": 3,
  "task": 1,
  "total_tasks": 2,
  "status": "paused",
  "completed_tasks": [
    {"id": "09-01", "name": "Backend foundation (model, migration, service, tests)", "status": "done", "commit": "f6ddfa5"},
    {"id": "09-02-t1", "name": "Metadata config auto-fill toggle + type selector", "status": "done", "commit": "e27a78a"},
    {"id": "09-02-t2", "name": "Asset detail dialog inference badge + rescore toast", "status": "done", "commit": "911ca77"},
    {"id": "09-02-t3", "name": "Visual verification checkpoint", "status": "done", "progress": "User approved after bug fixes"},
    {"id": "09-session-fixes", "name": "Fix default_metadata_values name->UUID normalization (backend + frontend)", "status": "done", "commit": "uncommitted - 4 files modified"}
  ],
  "remaining_tasks": [
    {"id": "09-03-t1", "name": "Wire auto-fill into harmonizer._ensure_asset + scheduler fires tasks after commit", "status": "in_progress", "progress": "harmonizer.py: added import uuid + Tuple only. All method changes pending."},
    {"id": "09-03-t2", "name": "Scoring reset on metadata PATCH + ai_inference_status in asset detail response", "status": "not_started"}
  ],
  "blockers": [],
  "human_actions_pending": [
    {
      "action": "Run docker-compose exec backend alembic upgrade head if not already done",
      "context": "Phase 09 migration: auto_fill_enabled/auto_fill_type on metadata_fields, ai_inference_tracking table",
      "blocking": false
    }
  ],
  "decisions": [
    {"decision": "Auto-fill hook goes in harmonizer._ensure_asset NOT sync services", "rationale": "CreativeAsset created in harmonizer only; sync services write raw perf tables", "phase": "09"},
    {"decision": "Thread _new_asset_ids list through call chain; fire tasks in scheduler.py AFTER db.commit()", "rationale": "ai_autofill.py opens own session via get_session_factory() - needs committed data", "phase": "09"},
    {"decision": "_harmonize_with_deadlock_retry creates new_assets=[], returns (count, new_assets)", "rationale": "8 call sites in scheduler.py unpack and fire tasks after commit", "phase": "09"},
    {"decision": "Fix default_metadata_values: normalize name->UUID on read in dashboard.py", "rationale": "Existing DB data name-keyed due to platforms UI bug; read-time fix needs no migration", "phase": "09"}
  ],
  "uncommitted_files": [
    "backend/app/api/v1/endpoints/dashboard.py - default_metadata_values name->UUID normalization",
    "backend/app/services/sync/harmonizer.py - partial: import uuid + Tuple added only",
    "frontend/src/app/features/configuration/pages/platforms.component.ts - key defaults by field.id",
    "frontend/src/app/features/dashboard/dashboard.component.ts - removed debug console.logs"
  ],
  "next_action": "Complete harmonizer.py: add _new_asset_ids: Optional[List[Tuple[uuid.UUID, uuid.UUID]]] = None to harmonize_connection, all _harmonize_* methods, and _ensure_asset. In _ensure_asset new-asset branch after db.flush(), append (asset.id, asset.organization_id) if _new_asset_ids is not None. Thread param through. Then scheduler.py: update _harmonize_with_deadlock_retry to return (count, new_assets); update 8 call sites to unpack + fire run_autofill_for_asset tasks after db.commit(). Then assets.py Task 2.",
  "context_notes": "CreativeAsset created in harmonizer._ensure_asset (flush only, no commit). Commit is in scheduler.py. ai_autofill.py uses own session so must run after commit. harmonizer.py only has import changes applied - all signature/body changes still needed. 4 session-fix files uncommitted - commit with 09-03 work."
}
